{
  "trades": [
    {
      "costs": [
        {
          "ingredient": {
            "item": "minecraft:emerald"
          },
          "count": 1
        }
      ],
      "result": [
        {
          "id": "minecraft:redstone",
          "Count": 10
        }
      ],
      "type": "terra_entity:ingredient_trade_item_list"
    },
    {
      "costs": [
        {
          "ingredient": {
            "item": "minecraft:emerald"
          },
          "count": 1
        }
      ],
      "result": [
        {
          "id": "minecraft:repeater",
          "Count": 5
        }
      ],
      "type": "terra_entity:ingredient_trade_item_list"
    },
    {
      "costs": [
        {
          "ingredient": {
            "item": "minecraft:emerald"
          },
          "count": 1
        }
      ],
      "result": [
        {
          "id": "minecraft:comparator",
          "Count": 5
        }
      ],
      "type": "terra_entity:ingredient_trade_item_list"
    },
    {
      "costs": [
        {
          "ingredient": {
            "item": "minecraft:emerald"
          },
          "count": 1
        }
      ],
      "result": [
        {
          "id": "minecraft:redstone_lamp",
          "Count": 5
        }
      ],
      "type": "terra_entity:ingredient_trade_item_list"
    },
    {
      "costs": [
        {
          "ingredient": {
            "item": "minecraft:emerald"
          },
          "count": 1
        }
      ],
      "result": [
        {
          "id": "minecraft:redstone_torch",
          "Count": 8
        }
      ],
      "type": "terra_entity:ingredient_trade_item_list"
    },
    {
      "costs": [
        {
          "ingredient": {
            "item": "minecraft:emerald"
          },
          "count": 20
        }
      ],
      "result": [
        {
          "id": "terra_entity:combat_wrench",
          "Count": 1,
          "tag": {
            "Damage": 0,
            "cafelib:boolean": "true"
          }
        }
      ],
      "type": "terra_entity:ingredient_trade_item_list"
    }
  ]
}